django_gpt/__init__.py
django_gpt/ai.py
django_gpt/models.py
django_gpt-1.0.1.dist-info/LICENSE
django_gpt-1.0.1.dist-info/METADATA
django_gpt-1.0.1.dist-info/WHEEL
django_gpt-1.0.1.dist-info/top_level.txt
django_gpt-1.0.1.dist-info/RECORD
