Metadata-Version: 2.1
Name: django-gpt
Version: 1.0.1
Summary: Integrate powerful text generators like GPT-3 and GPT-4 into your Django application for automated text generation based on instructions.
Home-page: https://github.com/markolofsen/django-gpt
Author: Mark
Author-email: markolofsen@gmail.com
Classifier: Programming Language :: Python :: 3
Classifier: License :: OSI Approved :: MIT License
Classifier: Operating System :: OS Independent
Requires-Python: >=3.6
License-File: LICENSE
Requires-Dist: openai
